form_core_pygame/__init__.py
form_core_pygame/container_base.py
form_core_pygame/container_floating_elements.py
form_core_pygame/container_grid.py
form_core_pygame/container_label_checkbox.py
form_core_pygame/container_label_input_text.py
form_core_pygame/filesystem_utils.py
form_core_pygame/formulario_manager.py
form_core_pygame/widget_base.py
form_core_pygame/widget_checkbox.py
form_core_pygame/widget_custom_filedialog.py
form_core_pygame/widget_input_text.py
form_core_pygame/widget_label.py
form_core_pygame/widget_multi_list_selector.py
form_core_pygame/widget_radio_group.py
form_core_pygame/widget_single_list_selector.py
form_core_pygame/widget_text_area.py
form_core_pygame/assets/Fonts/Arial_Black.ttf
form_core_pygame/assets/Fonts/Comic_Sans_MS.ttf
form_core_pygame/assets/Fonts/Courier_New_Bold_Italic.ttf
form_core_pygame/assets/Fonts/Courier_New_Italic.ttf
form_core_pygame/assets/Fonts/DejaVuSansMono.ttf
form_core_pygame/assets/Fonts/Georgia_Italic.ttf
form_core_pygame/assets/Fonts/Impact.ttf
form_core_pygame/assets/Fonts/Leame.txt
form_core_pygame/assets/Fonts/PottiSreeramulu.ttf
form_core_pygame/assets/Fonts/Times_New_Roman_Italic.ttf
form_core_pygame/assets/Fonts/Trebuchet_MS_Bold_Italic.ttf
form_core_pygame/assets/Fonts/UbuntuMono-B.ttf
form_core_pygame/assets/Fonts/UbuntuMono-BI.ttf
form_core_pygame/assets/Fonts/UbuntuMono-R.ttf
form_core_pygame/assets/Fonts/UbuntuMono-RI.ttf
form_core_pygame/assets/Fonts/Verdana.ttf
form_core_pygame/assets/Fonts/Verdana_Bold_Italic.ttf
form_core_pygame/assets/Fonts/Verdana_Italic.ttf
form_core_pygame/assets/Fonts/Yrsa-Medium.ttf
form_core_pygame/assets/Fonts/Yrsa-MediumItalic.ttf
form_core_pygame/assets/Fonts/arialbd.ttf
form_core_pygame/assets/Fonts/ariali.ttf
form_core_pygame/assets/Fonts/freesansbold.ttf
form_core_pygame/assets/styles/helpview.json
form_core_pygame/assets/styles/popup_gui.json
form_core_pygame-0.1.1.dist-info/licenses/LICENSE.md
form_core_pygame-0.1.1.dist-info/METADATA
form_core_pygame-0.1.1.dist-info/WHEEL
form_core_pygame-0.1.1.dist-info/top_level.txt
form_core_pygame-0.1.1.dist-info/RECORD
