Metadata-Version: 2.4
Name: form-core-pygame
Version: 0.1.1
Summary: Form and widget core toolkit for Pygame
Author-email: Antonio Castro Snurmacher <acastro0841@gmail.com>
License-Expression: MIT
Project-URL: Homepage, https://github.com/acastr008/form_core_pygame
Project-URL: Source, https://github.com/acastr008/form_core_pygame
Project-URL: Issues, https://github.com/acastr008/form_core_pygame/issues
Keywords: pygame,gui,forms,widgets,formulario
Classifier: Programming Language :: Python :: 3
Classifier: Topic :: Software Development :: User Interfaces
Classifier: Topic :: Games/Entertainment
Requires-Python: >=3.9
License-File: LICENSE.md
Requires-Dist: pygame>=2.0
Dynamic: license-file
